{
  "success": true,
  "data": [
    {
      "id": "ntf_mock_001",
      "userId": "usr_mock_004",
      "transactionId": "txn_mock_002",
      "type": "funding",
      "title": "Funding confirmed",
      "message": "Payment was confirmed on NT-2026-000179. The land transaction record has been updated.",
      "read": false,
      "createdAt": "2026-07-14T08:45:00Z",
      "link": "/app"
    },
    {
      "id": "ntf_mock_002",
      "userId": "usr_mock_004",
      "invitationId": "inv_mock_001",
      "type": "deal",
      "title": "New deal invitation",
      "message": "Damilola Properties Ltd invited you to a property transaction: Two-bedroom apartment reservation.",
      "read": false,
      "createdAt": "2026-07-13T10:21:00Z",
      "link": "/app/invitations/inv_mock_001"
    },
    {
      "id": "ntf_mock_003",
      "userId": "usr_mock_004",
      "transactionId": "txn_mock_003",
      "type": "evidence",
      "title": "Evidence submitted",
      "message": "Lekki Gardens Development Co. uploaded property documents on NT-2026-000171. Review them in the transaction room.",
      "read": false,
      "createdAt": "2026-07-12T16:10:00Z",
      "link": "/app"
    },
    {
      "id": "ntf_mock_004",
      "userId": "usr_mock_004",
      "transactionId": "txn_mock_004",
      "type": "dispute",
      "title": "Dispute opened",
      "message": "A dispute was opened on NT-2026-000160 with Bright Homes Realty. Add your response and evidence.",
      "read": true,
      "createdAt": "2026-07-10T11:30:00Z",
      "link": "/app"
    },
    {
      "id": "ntf_mock_005",
      "userId": "usr_mock_004",
      "type": "verification",
      "title": "Verify your email",
      "message": "Confirm your email address to unlock safe deals and protected funding.",
      "read": true,
      "createdAt": "2026-07-08T09:00:00Z"
    },
    {
      "id": "ntf_mock_006",
      "userId": "usr_mock_004",
      "type": "system",
      "title": "Welcome to Naitrust",
      "message": "Create a property transaction, document the participants and terms, and keep payments and supporting evidence in one room.",
      "read": true,
      "createdAt": "2026-07-05T12:00:00Z"
    }
  ]
}
